logx/__init__.py
logx/gumph.py
logx/logxintrospect.py
logxutil/__init__.py
logxutil/util.py
logx-0.1.1562053912.dist-info/WHEEL
logx-0.1.1562053912.dist-info/METADATA
logx-0.1.1562053912.dist-info/RECORD
