Metadata-Version: 2.1
Name: logx
Version: 0.1.1562053912
Summary: best practice python logging with zero config
Home-page: https://github.com/djrobstep/logx
License: Unlicense
Author: Robert Lechte
Author-email: robertlechte@gmail.com
Classifier: License :: Other/Proprietary License
Classifier: Programming Language :: Python :: 2
Classifier: Programming Language :: Python :: 2.7
Classifier: Programming Language :: Python :: 3
Classifier: Programming Language :: Python :: 3.4
Classifier: Programming Language :: Python :: 3.5
Classifier: Programming Language :: Python :: 3.6
Classifier: Programming Language :: Python :: 3.7
Requires-Dist: logging_tree
Requires-Dist: pyyaml
Project-URL: Repository, https://github.com/djrobstep/logx
